README.md
setup.py
youtube_playlist_creator_bot/__init__.py
youtube_playlist_creator_bot.egg-info/PKG-INFO
youtube_playlist_creator_bot.egg-info/SOURCES.txt
youtube_playlist_creator_bot.egg-info/dependency_links.txt
youtube_playlist_creator_bot.egg-info/requires.txt
youtube_playlist_creator_bot.egg-info/top_level.txt