Metadata-Version: 2.1
Name: youtube-playlist-creator-bot
Version: 1.0.0
Summary: A python library to create playlist on youtube automatically.
Home-page: https://youtube-api.datakund.com/en/latest/
Author: DataKund
Author-email: datakund@gmail.com
License: Apache License 2.0
Keywords: youtube python bot_studio automation playlist create login
Platform: UNKNOWN
